chromy/__init__.py
chromy/blueprint_files.py
chromy/chromy.py
chromy/theme.py
chromy/managers/__init__.py
chromy/managers/exceptions.py
chromy/managers/manifest.py
chromy/managers/permissions.py
chromy_cli-0.1.1.dist-info/METADATA
chromy_cli-0.1.1.dist-info/WHEEL
chromy_cli-0.1.1.dist-info/entry_points.txt
chromy_cli-0.1.1.dist-info/top_level.txt
chromy_cli-0.1.1.dist-info/RECORD
