Metadata-Version: 2.2
Name: chromy-cli
Version: 0.1.1
Summary: A simple CLI to create and manage Chrome extensions.
Author-email: mvlware <mal@mvlware.xyz>
License: MIT
Classifier: Programming Language :: Python :: 3
Classifier: License :: OSI Approved :: MIT License
Classifier: Operating System :: OS Independent
Classifier: Development Status :: 3 - Alpha
Requires-Python: >=3.8
Requires-Dist: colorama
Requires-Dist: blessed
Requires-Dist: inquirer
